{
  "toast": {
    "close_button_color": "#626e84",
    "success": {
      "background_color": "#ffffff",
      "foreground_color": "#1b2c48",
      "icon_color": "#09b581"
    },
    "warning": {
      "background_color": "#ffffff",
      "foreground_color": "#1b2c48",
      "icon_color": "#f8c73e"
    },
    "info": {
      "background_color": "#ffffff",
      "foreground_color": "#1b2c48",
      "icon_color": "#6e5ddb"
    },
    "action": {
      "background_color": "#ffffff",
      "foreground_color": "#1b2c48",
      "icon_color": "#4856CB"
    },
    "error": {
      "background_color": "#ffffff",
      "foreground_color": "#1b2c48",
      "icon_color": "#e22245"
    },
    "heading": {
      "fontFamily": "Urbanist",
      "lineHeight": "24px",
      "fontSize": "16px",
      "fontWeight": 700
    },
    "text": {
      "fontFamily": "Noto Sans",
      "lineHeight": "18px",
      "fontSize": "12px",
      "fontWeight": 400
    },
    "margin": "16px",
    "gap": "12px",
    "gap_text": "4px",
    "gap_button": "16px",
    "button_bar": {
      "gap": "8px"
    },
    "border_radius": "8px",
    "box_shadow": {
      "x": 0,
      "y": "2px",
      "blur": "4px",
      "spread": "1px",
      "color": "#23395c1a",
      "type": "dropShadow"
    },
    "icon": "24px",
    "wrapping_width": "320px",
    "stacking": {
      "gap": "4px"
    }
  },
  "modal": {
    "close_button_color": "#626e84",
    "header_color": "#1b2c48",
    "background_color": "#ffffff",
    "shroud_color": "#23395dcc",
    "header": {
      "gap": "12px"
    },
    "padding": "32px",
    "gap": "16px",
    "heading": {
      "fontFamily": "Urbanist",
      "lineHeight": "32px",
      "fontSize": "24px",
      "fontWeight": 700,
      "letterSpacing": "2%"
    },
    "icon": "32px",
    "small": {
      "width": "420px"
    },
    "medium": {
      "width": "680px"
    },
    "large": {
      "width": "800px"
    },
    "button_bar": {
      "gap": "8px"
    },
    "box_shadow": {
      "x": 0,
      "y": "6px",
      "blur": "8px",
      "spread": "1px",
      "color": "#23395c26",
      "type": "dropShadow"
    },
    "border_radius": "16px",
    "shroud": {
      "opacity": 0.8
    },
    "dismiss_button": {
      "padding_top": "16px",
      "padding_right": "8px"
    }
  },
  "popover": {
    "border_radius": "8px",
    "box_shadow": {
      "x": 0,
      "y": "6px",
      "blur": "8px",
      "spread": "1px",
      "color": "#23395c26",
      "type": "dropShadow"
    },
    "close_button_color": "#626e84",
    "header_color": "#1b2c48",
    "background_color": "#ffffff",
    "gap": "16px",
    "padding": "24px",
    "buttons_bar": {
      "gap": "8px"
    },
    "header": {
      "gap": "4px"
    },
    "spacer": {
      "height": "16px"
    },
    "body": {
      "text": {
        "fontFamily": "Noto Sans",
        "fontWeight": 400,
        "lineHeight": "20px",
        "fontSize": "14px"
      }
    },
    "title": {
      "text": {
        "fontFamily": "Urbanist",
        "fontWeight": 700,
        "lineHeight": "24px",
        "fontSize": "16px"
      }
    },
    "anchor": {
      "width": "13px",
      "height": "13px"
    }
  },
  "progress_and_loading": {
    "spinner": {
      "foreground": "#4856CB",
      "base": "#CED2FC",
      "large": 48,
      "small": 16,
      "text": {
        "fontFamily": "Noto Sans",
        "fontWeight": 600,
        "lineHeight": "18px",
        "fontSize": "12px"
      }
    },
    "text_color": "#1b2c48",
    "loading_state": {
      "large": {
        "header": {
          "fontFamily": "Urbanist",
          "fontWeight": 700,
          "lineHeight": "32px",
          "fontSize": "24px"
        },
        "subheader": {
          "fontFamily": "Noto Sans",
          "fontWeight": 600,
          "lineHeight": "24px",
          "fontSize": "16px"
        },
        "width": "600px"
      },
      "medium": {
        "header": {
          "fontFamily": "Urbanist",
          "fontWeight": 700,
          "lineHeight": "27px",
          "fontSize": "18px"
        },
        "subheader": {
          "fontFamily": "Noto Sans",
          "fontWeight": 600,
          "lineHeight": "20px",
          "fontSize": "14px"
        },
        "width": "400px"
      },
      "small": {
        "header": {
          "fontFamily": "Urbanist",
          "fontWeight": 700,
          "lineHeight": "24px",
          "fontSize": "16px"
        },
        "subheader": {
          "fontFamily": "Noto Sans",
          "fontWeight": 600,
          "lineHeight": "18px",
          "fontSize": "12px"
        },
        "width": "200px"
      }
    },
    "large": {
      "gap": "24px",
      "gap_text": "4px"
    },
    "page_loading": {
      "gap": "-3px"
    },
    "medium": {
      "gap": "16px",
      "gap_text": "4px"
    },
    "small": {
      "gap": "12px",
      "gap_text": "4px"
    },
    "blank_state": {
      "large": {
        "header": {
          "fontFamily": "Urbanist",
          "fontWeight": 700,
          "lineHeight": "27px",
          "fontSize": "18px"
        },
        "subheader": {
          "fontFamily": "Noto Sans",
          "fontWeight": 600,
          "lineHeight": "20px",
          "fontSize": "14px"
        }
      },
      "small": {
        "header": {
          "fontFamily": "Urbanist",
          "fontWeight": 700,
          "lineHeight": "24px",
          "fontSize": "14px"
        },
        "subheader": {
          "fontFamily": "Noto Sans",
          "fontWeight": 600,
          "lineHeight": "18px",
          "fontSize": "12px"
        }
      }
    },
    "large_border": 4,
    "small_border": 2,
    "thin_border": 1
  },
  "blank_state": {
    "small": {
      "width": "250px",
      "max_width": "569px"
    },
    "large": {
      "min_width": "570px"
    },
    "icon": {
      "size": {
        "sm": "32px",
        "lg": "42px"
      }
    },
    "padding": "32px 16px",
    "gap_message": "4px",
    "gap_main": "12px",
    "gap_content": "24px",
    "icon_color": "#767c8d",
    "foreground_color": "#1b2c48",
    "background_color": "#fbfcfe",
    "border_radius": "8px"
  }
}
