{
  "form_control": {
    "input": {
      "content_text": {
        "value": "{body.sm.regular}",
        "type": "typography"
      },
      "default": {
        "border": {
          "value": {
            "color": "{border.form_control.text_input.default}",
            "width": "{form_control.text_input.edges.border_width}",
            "style": "solid"
          },
          "type": "border"
        }
      },
      "hover": {
        "border": {
          "value": {
            "color": "{border.form_control.text_input.hover}",
            "width": "{form_control.text_input.edges.border_width}",
            "style": "solid"
          },
          "type": "border"
        }
      },
      "active": {
        "border": {
          "value": {
            "color": "{border.form_control.text_input.active}",
            "width": "{form_control.text_input.edges.border_width}",
            "style": "solid"
          },
          "type": "border"
        }
      },
      "error": {
        "border": {
          "value": {
            "color": "{border.form_control.text_input.error}",
            "width": "{form_control.text_input.edges.border_width}",
            "style": "solid"
          },
          "type": "border"
        }
      },
      "disabled": {
        "border": {
          "value": {
            "color": "{border.form_control.text_input.default}",
            "width": "{form_control.text_input.edges.border_width}",
            "style": "solid"
          },
          "type": "border"
        },
        "opacity": {
          "value": "{opacity.disabled}",
          "type": "opacity"
        }
      },
      "border_radius": {
        "value": "{theme.border_radius.form_control.input.medium}",
        "type": "borderRadius"
      },
      "background_color": {
        "value": "{background.form_control.text_input.track}",
        "type": "color"
      },
      "placeholder_color": {
        "value": "{foreground.form_control.text_input.placeholder}",
        "type": "color"
      },
      "suggestion_color": {
        "value": "{foreground.form_control.text_input.placeholder}",
        "type": "color"
      },
      "populated_color": {
        "value": "{foreground.form_control.text_input.populated}",
        "type": "color"
      },
      "input_clearable": {
        "input_clearable_color": {
          "value": "{foreground.form_control.text_input.icon}",
          "type": "color"
        },
        "size": {
          "value": "{assets.sm.size}",
          "type": "sizing"
        }
      },
      "gap": {
        "value": "{form_control.field.text_input.gap}",
        "type": "spacing"
      },
      "top": {
        "value": "{spacing.3xs}",
        "type": "spacing"
      },
      "padding": {
        "value": "{form_control.field.text_input.small.padding} {form_control.field.text_input.medium.padding}",
        "type": "spacing"
      },
      "prefix_sufix": {
        "text": {
          "value": "{body.md.bold}",
          "type": "typography"
        },
        "height": {
          "value": "{container.sm.height}",
          "type": "sizing"
        },
        "default_color": {
          "value": "{foreground.form_control.text_input.placeholder}",
          "type": "color"
        }
      },
      "textfield": {
        "height": {
          "value": "{form_control.field.text_input.md.height}",
          "type": "sizing"
        },
        "min_width": {
          "value": "{form_control.field.text_input.min_width}",
          "type": "sizing"
        }
      },
      "color_picker": {
        "size": {
          "value": "{form_control.field.text_input.md.height}",
          "type": "sizing"
        }
      },
      "input_icon": {
        "size": {
          "value": "{assets.sm.size}",
          "type": "sizing"
        },
        "default_color": {
          "value": "{foreground.form_control.text_input.populated}",
          "type": "color"
        },
        "icon_end_color": {
          "value": "{foreground.form_control.text_input.icon}",
          "type": "color"
        }
      },
      "focus_ring": {
        "default_color": {
          "value": "{border.focus}",
          "type": "color"
        }
      },
      "textarea": {
        "height": {
          "value": "{form_control.field.text_input.lg.height}",
          "type": "sizing"
        }
      },
      "focus": {
        "border": {
          "value": {
            "color": "{border.focus}",
            "width": "{focus_outline.md.border_width}",
            "style": "solid"
          },
          "type": "border"
        }
      },
      "spinbutton_icon": {
        "size": {
          "value": "{assets.sm.size}",
          "type": "sizing"
        }
      },
      "focus_selection": {
        "background_color": {
          "value": "{border.focus}",
          "type": "color"
        }
      }
    },
    "label": {
      "padding": {
        "value": "0 0 {form_control.field.padding} 0",
        "type": "spacing"
      },
      "text": {
        "value": "{body.sm.regular}",
        "type": "typography"
      },
      "text_bold": {
        "value": "{body.sm.semi_bold}",
        "type": "typography"
      },
      "label_color": {
        "value": "{foreground.form_control.label.default}",
        "type": "color"
      },
      "indicator": {
        "text": {
          "value": "{body.sm.regular}",
          "type": "typography"
        },
        "required_color": {
          "value": "{foreground.form_control.label.required_accent}",
          "type": "color"
        },
        "optional_color": {
          "value": "{foreground.form_control.label.optional_accent}",
          "type": "color"
        }
      },
      "icon_size": {
        "value": "{assets.sm.size}",
        "type": "sizing"
      },
      "tooltip_trigger": {
        "color": {
          "value": "{foreground.form_control.label.tooltip}",
          "type": "color"
        },
        "border_radius": {
          "value": "{theme.border_radius.focus.xsmall}",
          "type": "borderRadius"
        }
      }
    },
    "form_field": {
      "gap": {
        "value": "{form_control.field.gap}",
        "type": "spacing"
      }
    },
    "group": {
      "gap_items": {
        "value": "{form_control.field.grouped_input.gap}",
        "type": "spacing"
      }
    },
    "helper": {
      "gap": {
        "value": "{form_control.field.gap}",
        "type": "spacing"
      },
      "helper_text": {
        "value": "{body.sm.regular}",
        "type": "typography"
      },
      "padding": {
        "value": "{form_control.field.padding} 0 0 0",
        "type": "spacing"
      },
      "icon": {
        "padding": {
          "value": "1px 0 1px 0",
          "type": "spacing"
        }
      },
      "padding_small": {
        "value": "{form_control.field.gap} 0 0 0",
        "type": "spacing"
      },
      "error_padding": {
        "value": "{form_control.field.gap} 0 0 0",
        "type": "spacing"
      },
      "default_color": {
        "value": "{foreground.form_control.help_text.default}",
        "type": "color"
      },
      "error_color": {
        "value": "{foreground.form_control.help_text.error}",
        "type": "color"
      },
      "icon_size": {
        "value": "{assets.sm.size}",
        "type": "sizing"
      }
    },
    "spin_button": {
      "gap": {
        "value": "{form_control.field.grouped_input.gap}",
        "type": "spacing"
      }
    },
    "spinner": {
      "track": {
        "value": "{background.system.progress_and_loading.progressed}",
        "type": "color"
      },
      "error_color": {
        "value": "{background.system.progress_and_loading.default}",
        "type": "color"
      }
    },
    "textarea": {
      "padding": {
        "value": "{form_control.field.text_input.small.padding}",
        "type": "spacing"
      }
    },
    "focus_ring": {
      "border_radius": {
        "value": "{theme.border_radius.form_control.input.medium}",
        "type": "borderRadius"
      }
    }
  }
}