{
  "theme": {
    "font_family": {
      "headings": {
        "value": "{font_family.roboto}",
        "type": "fontFamilies",
        "description": "The font family we use for headings and subheadings in this theme."
      },
      "body": {
        "value": "{font_family.roboto}",
        "type": "fontFamilies",
        "description": "The font family we use for body and labels in this theme."
      },
      "code": {
        "body": {
          "value": "{font_family.noto_sans_mono}",
          "type": "fontFamilies",
          "description": "The font family that is used for code blocks and snippets."
        }
      }
    },
    "background": {
      "container": {
        "primary": {
          "10": {
            "value": "{color.white}",
            "type": "color"
          },
          "20": {
            "value": "{color_legacy.grey.100}",
            "type": "color"
          },
          "30": {
            "value": "{color_legacy.grey.90}",
            "type": "color"
          },
          "40": {
            "value": "{color_legacy.grey.70}",
            "type": "color"
          },
          "45": {
            "value": "{color.genesys_navy.50}",
            "type": "color"
          },
          "50": {
            "value": "{color_legacy.blue.100}",
            "type": "color"
          },
          "60": {
            "value": "{color_legacy.grey.60}",
            "type": "color"
          }
        },
        "secondary": {
          "10": {
            "value": "{color_legacy.blue.60}",
            "type": "color"
          },
          "20": {
            "value": "{color_legacy.blue.50}",
            "type": "color"
          },
          "30": {
            "value": "{color_legacy.blue.40}",
            "type": "color"
          }
        },
        "tertiary": {
          "10": {
            "value": "{color.transparent}",
            "type": "color"
          },
          "20": {
            "value": "{color_legacy.black.100}",
            "type": "color"
          }
        },
        "high_contrast": {
          "10": {
            "value": "{color_legacy.black.40}",
            "type": "color"
          },
          "20": {
            "value": "{color_legacy.blue.20}",
            "type": "color"
          },
          "30": {
            "value": "{color_legacy.blue.10}",
            "type": "color"
          },
          "40": {
            "value": "{color.black}",
            "type": "color"
          }
        },
        "global_nav": {
          "desktop": {
            "10": {
              "value": "{color.white}",
              "type": "color"
            },
            "20": {
              "value": "{color.genesys_navy.600}",
              "type": "color"
            },
            "30": {
              "value": "{color.genesys_navy.800}",
              "type": "color"
            },
            "40": {
              "value": "{color.genesys_navy.700}",
              "type": "color"
            },
            "50": {
              "value": "{color.genesys_navy.800}",
              "type": "color"
            }
          },
          "mobile": {
            "10": {
              "value": "{color.haze.950}",
              "type": "color"
            },
            "20": {
              "value": "{color.genesys_navy.100}",
              "type": "color"
            }
          }
        }
      },
      "form_control": {
        "input": {
          "10": {
            "value": "{color_legacy.grey.90}",
            "type": "color"
          },
          "20": {
            "value": "{color_legacy.black.100}",
            "type": "color"
          }
        }
      },
      "overlay": {
        "10": {
          "value": "{color_legacy.black.30}",
          "type": "color",
          "$extensions": {
            "studio.tokens": {
              "modify": {
                "type": "alpha",
                "value": "{opacity.64}",
                "space": "srgb"
              }
            }
          }
        }
      },
      "system": {
        "primary": {
          "10": {
            "value": "{color_legacy.blue.100}",
            "type": "color"
          },
          "20": {
            "value": "{color_legacy.blue.80}",
            "type": "color"
          },
          "30": {
            "value": "{color_legacy.blue.60}",
            "type": "color"
          },
          "40": {
            "value": "{color_legacy.blue.50}",
            "type": "color"
          },
          "50": {
            "value": "{color_legacy.blue.30}",
            "type": "color"
          }
        },
        "info": {
          "5": {
            "value": "{color_legacy.blue.100}",
            "type": "color"
          },
          "10": {
            "value": "{color_legacy.blue.100}",
            "type": "color"
          },
          "20": {
            "value": "{color_legacy.blue.80}",
            "type": "color"
          },
          "30": {
            "value": "{color_legacy.blue.60}",
            "type": "color"
          },
          "40": {
            "value": "{color_legacy.blue.30}",
            "type": "color"
          },
          "50": {
            "value": "{color_legacy.blue.10}",
            "type": "color"
          }
        },
        "success": {
          "5": {
            "value": "{color_legacy.green.100}",
            "type": "color"
          },
          "10": {
            "value": "{color_legacy.green.100}",
            "type": "color"
          },
          "20": {
            "value": "{color_legacy.green.80}",
            "type": "color"
          },
          "30": {
            "value": "{color_legacy.green.80}",
            "type": "color"
          },
          "35": {
            "value": "{color_legacy.green.60}",
            "type": "color"
          },
          "40": {
            "value": "{color_legacy.green.30}",
            "type": "color"
          },
          "50": {
            "value": "{color_legacy.green.10}",
            "type": "color"
          }
        },
        "warning": {
          "5": {
            "value": "{color_legacy.yellow.100}",
            "type": "color"
          },
          "10": {
            "value": "{color_legacy.yellow.100}",
            "type": "color"
          },
          "20": {
            "value": "{color_legacy.yellow.80}",
            "type": "color"
          },
          "30": {
            "value": "{color_legacy.yellow.60}",
            "type": "color"
          },
          "40": {
            "value": "{color_legacy.yellow.30}",
            "type": "color"
          },
          "50": {
            "value": "{color_legacy.yellow.10}",
            "type": "color"
          }
        },
        "error": {
          "5": {
            "value": "{color_legacy.red.100}",
            "type": "color"
          },
          "10": {
            "value": "{color_legacy.red.100}",
            "type": "color"
          },
          "20": {
            "value": "{color_legacy.red.80}",
            "type": "color"
          },
          "30": {
            "value": "{color_legacy.red.60}",
            "type": "color"
          },
          "40": {
            "value": "{color_legacy.red.30}",
            "type": "color"
          },
          "50": {
            "value": "{color_legacy.red.10}",
            "type": "color"
          }
        }
      },
      "custom_accents": {
        "bold": {
          "10": {
            "value": "{color_legacy.secondary.navy}",
            "type": "color"
          },
          "20": {
            "value": "{color_legacy.blue.40}",
            "type": "color"
          },
          "30": {
            "value": "{color_legacy.secondary.lilac}",
            "type": "color"
          },
          "40": {
            "value": "{color_legacy.green.30}",
            "type": "color"
          },
          "50": {
            "value": "{color_legacy.black.20}",
            "type": "color"
          },
          "60": {
            "value": "{color_legacy.secondary.genesys_blue}",
            "type": "color"
          },
          "70": {
            "value": "{color_legacy.secondary.electric_purple}",
            "type": "color"
          },
          "80": {
            "value": "{color_legacy.secondary.plum}",
            "type": "color"
          },
          "90": {
            "value": "{color_legacy.secondary.pink}",
            "type": "color"
          },
          "100": {
            "value": "{color_legacy.yellow.20}",
            "type": "color"
          },
          "110": {
            "value": "{color_legacy.secondary.yellow_green}",
            "type": "color"
          },
          "120": {
            "value": "{color_legacy.yellow.120}",
            "type": "color"
          },
          "130": {
            "value": "{color_legacy.secondary.genesys_blue}",
            "type": "color"
          }
        },
        "subtle": {
          "10": {
            "value": "{color_legacy.data_visualization.navy}",
            "type": "color"
          },
          "20": {
            "value": "{color_legacy.data_visualization.genesys_blue}",
            "type": "color"
          },
          "30": {
            "value": "{color_legacy.data_visualization.lilac}",
            "type": "color"
          },
          "40": {
            "value": "{color_legacy.green.90}",
            "type": "color"
          },
          "50": {
            "value": "{color_legacy.grey.40}",
            "type": "color"
          },
          "60": {
            "value": "{color_legacy.data_visualization.genesys_blue}",
            "type": "color"
          },
          "70": {
            "value": "{color_legacy.data_visualization.electric_purple}",
            "type": "color"
          },
          "80": {
            "value": "{color_legacy.data_visualization.plum}",
            "type": "color"
          },
          "90": {
            "value": "{color_legacy.data_visualization.pink}",
            "type": "color"
          },
          "100": {
            "value": "{color_legacy.yellow.80}",
            "type": "color"
          },
          "110": {
            "value": "{color_legacy.data_visualization.yellow_green}",
            "type": "color"
          },
          "120": {
            "value": "{color_legacy.yellow.110}",
            "type": "color"
          }
        },
        "color_swatch": {
          "10": {
            "value": "{color.genesys_orange.500}",
            "type": "color",
            "description": "This color is used for color swatches, for eg. in the Rich Text Editor's text highlight menu."
          },
          "20": {
            "value": "{color.coral.300}",
            "type": "color",
            "description": "This color is used for color swatches, for eg. in the Rich Text Editor's text highlight menu."
          },
          "30": {
            "value": "{color.pear.400}",
            "type": "color",
            "description": "This color is used for color swatches, for eg. in the Rich Text Editor's text highlight menu."
          },
          "40": {
            "value": "{color.mango.500}",
            "type": "color",
            "description": "This color is used for color swatches, for eg. in the Rich Text Editor's text highlight menu."
          },
          "50": {
            "value": "{color.raspberry.300}",
            "type": "color",
            "description": "This color is used for color swatches, for eg. in the Rich Text Editor's text highlight menu."
          },
          "60": {
            "value": "{color.azure_blue.200}",
            "type": "color",
            "description": "This color is used for color swatches, for eg. in the Rich Text Editor's text highlight menu."
          },
          "70": {
            "value": "{color.mineral.300}",
            "type": "color",
            "description": "This color is used for color swatches, for eg. in the Rich Text Editor's text highlight menu."
          },
          "80": {
            "value": "{color.island.300}",
            "type": "color",
            "description": "This color is used for color swatches, for eg. in the Rich Text Editor's text highlight menu."
          }
        },
        "status": {
          "10": {
            "value": "{color.emerald.500}",
            "type": "color"
          },
          "20": {
            "value": "{color.pepper.500}",
            "type": "color"
          },
          "30": {
            "value": "{color.honey.500}",
            "type": "color"
          },
          "40": {
            "value": "{color.azure_blue.600}",
            "type": "color"
          },
          "50": {
            "value": "{color.haze.600}",
            "type": "color"
          },
          "60": {
            "value": "{color.raspberry.700}",
            "type": "color"
          },
          "70": {
            "value": "{color.genesys_orange.500}",
            "type": "color"
          }
        },
        "chat_bubble": {
          "10": {
            "value": "{color.haze.50}",
            "type": "color"
          },
          "20": {
            "value": "{color.island.50}",
            "type": "color"
          },
          "30": {
            "value": "{color.genesys_orange.50}",
            "type": "color"
          },
          "40": {
            "value": "{color.mango.100}",
            "type": "color"
          },
          "50": {
            "value": "{color.plum.100}",
            "type": "color"
          },
          "10d": {
            "value": "{color.haze.1000}",
            "type": "color"
          },
          "20d": {
            "value": "{color.island.950}",
            "type": "color"
          },
          "30d": {
            "value": "{color.genesys_orange.950}",
            "type": "color"
          },
          "40d": {
            "value": "{color.honey.900}",
            "type": "color"
          },
          "50d": {
            "value": "{color.plum.1000}",
            "type": "color"
          }
        },
        "ai": {
          "10": {
            "value": "{color.island.100}",
            "type": "color"
          },
          "20": {
            "value": "{color.violet.200}",
            "type": "color"
          },
          "20d": {
            "value": "{color.violet.700}",
            "type": "color"
          },
          "10d": {
            "value": "{color.island.700}",
            "type": "color"
          }
        },
        "global_nav": {
          "10": {
            "value": "{color.azure_blue.700}",
            "type": "color"
          },
          "20": {
            "value": "{color.azure_blue.600}",
            "type": "color"
          },
          "30": {
            "value": "{color.azure_blue.500}",
            "type": "color"
          }
        }
      }
    },
    "foreground": {
      "primary": {
        "10": {
          "value": "{color_legacy.black.70}",
          "type": "color"
        },
        "20": {
          "value": "{color_legacy.black.50}",
          "type": "color"
        },
        "30": {
          "value": "{color_legacy.black.50}",
          "type": "color"
        }
      },
      "secondary": {
        "10": {
          "value": "{color.white}",
          "type": "color"
        },
        "20": {
          "value": "{color_legacy.black.90}",
          "type": "color"
        },
        "30": {
          "value": "{color_legacy.black.80}",
          "type": "color"
        }
      },
      "tertiary": {
        "10": {
          "value": "{color_legacy.blue.60}",
          "type": "color"
        },
        "20": {
          "value": "{color_legacy.black.50}",
          "type": "color"
        },
        "30": {
          "value": "{color_legacy.black.50}",
          "type": "color"
        },
        "05": {
          "value": "{color_legacy.blue.80}",
          "type": "color"
        }
      },
      "high_contrast": {
        "10": {
          "value": "{color.white}",
          "type": "color"
        },
        "20": {
          "value": "{color_legacy.grey.80}",
          "type": "color"
        },
        "30": {
          "value": "{color_legacy.grey.30}",
          "type": "color"
        }
      },
      "system": {
        "primary": {
          "10": {
            "value": "{color_legacy.blue.60}",
            "type": "color"
          }
        },
        "info": {
          "10": {
            "value": "{color_legacy.blue.60}",
            "type": "color"
          }
        },
        "success": {
          "10": {
            "value": "{color_legacy.green.60}",
            "type": "color"
          }
        },
        "warning": {
          "10": {
            "value": "{color_legacy.yellow.60}",
            "type": "color"
          }
        },
        "error": {
          "10": {
            "value": "{color_legacy.red.60}",
            "type": "color"
          }
        }
      },
      "special_accents": {
        "brand": {
          "10": {
            "value": "{color.genesys_orange.500}",
            "type": "color"
          },
          "20": {
            "value": "{color.genesys_navy.950}",
            "type": "color"
          },
          "10d": {
            "value": "{color.genesys_orange.500}",
            "type": "color"
          },
          "20d": {
            "value": "{color.white}",
            "type": "color"
          }
        },
        "ai": {
          "10": {
            "value": "{color.plum.700}",
            "type": "color"
          }
        },
        "global_nav": {
          "desktop": {
            "10": {
              "value": "{color.white}",
              "type": "color"
            },
            "20": {
              "value": "{color.azure_blue.600}",
              "type": "color"
            },
            "30": {
              "value": "{color.azure_blue.700}",
              "type": "color"
            },
            "40": {
              "value": "{color.azure_blue.100}",
              "type": "color"
            },
            "50": {
              "value": "{color.genesys_navy.800}",
              "type": "color"
            }
          },
          "mobile": {
            "10": {
              "value": "{color.white}",
              "type": "color"
            },
            "10d": {
              "value": "{color.white}",
              "type": "color"
            }
          }
        }
      },
      "link": {
        "10": {
          "value": "{color_legacy.blue.60}",
          "type": "color"
        },
        "20": {
          "value": "{color_legacy.blue.50}",
          "type": "color"
        },
        "30": {
          "value": "{color_legacy.blue.40}",
          "type": "color"
        },
        "40": {
          "value": "{color_legacy.secondary.electric_purple}",
          "type": "color"
        }
      },
      "icon": {
        "10": {
          "value": "{color_legacy.black.50}",
          "type": "color"
        }
      },
      "form_control": {
        "click_input": {
          "10": {
            "value": "{color_legacy.blue.60}",
            "type": "color"
          },
          "20": {
            "value": "{color_legacy.blue.50}",
            "type": "color"
          },
          "30": {
            "value": "{color_legacy.blue.40}",
            "type": "color"
          },
          "40": {
            "value": "{color_legacy.black.100}",
            "type": "color"
          }
        }
      },
      "search": {
        "10": {
          "value": "{color.haze.900}",
          "type": "color"
        }
      },
      "custom_accents": {
        "ai": {
          "10": {
            "value": "{color.island.500}",
            "type": "color"
          },
          "20": {
            "value": "{color.violet.500}",
            "type": "color"
          },
          "10d": {
            "value": "{color.island.200}",
            "type": "color"
          },
          "20d": {
            "value": "{color.violet.300}",
            "type": "color"
          }
        }
      }
    },
    "border": {
      "focus": {
        "10": {
          "value": "{color_legacy.blue.90}",
          "type": "color"
        }
      },
      "divider": {
        "10": {
          "value": "{color.white}",
          "type": "color"
        },
        "20": {
          "value": "{color_legacy.grey.30}",
          "type": "color"
        },
        "30": {
          "value": "{color_legacy.blue.60}",
          "type": "color"
        }
      },
      "system": {
        "primary": {
          "10": {
            "value": "{color_legacy.blue.80}",
            "type": "color"
          }
        },
        "info": {
          "10": {
            "value": "{color_legacy.blue.80}",
            "type": "color"
          }
        },
        "success": {
          "10": {
            "value": "{color_legacy.green.80}",
            "type": "color"
          }
        },
        "warning": {
          "10": {
            "value": "{color_legacy.yellow.80}",
            "type": "color"
          }
        },
        "error": {
          "10": {
            "value": "{color_legacy.red.80}",
            "type": "color"
          },
          "20": {
            "value": "{color_legacy.red.60}",
            "type": "color"
          }
        }
      },
      "inputs": {
        "default": {
          "10": {
            "value": "{color_legacy.black.100}",
            "type": "color"
          }
        },
        "hover": {
          "10": {
            "value": "{color_legacy.blue.50}",
            "type": "color"
          }
        },
        "active": {
          "10": {
            "value": "{color_legacy.blue.60}",
            "type": "color"
          }
        }
      },
      "edges": {
        "default": {
          "0": {
            "value": "{color_legacy.grey.30}",
            "type": "color"
          },
          "5": {
            "value": "{color_legacy.grey.60}",
            "type": "color"
          },
          "10": {
            "value": "{color_legacy.grey.30}",
            "type": "color"
          },
          "20": {
            "value": "{color_legacy.black.80}",
            "type": "color"
          },
          "30": {
            "value": "{color_legacy.black.50}",
            "type": "color"
          }
        },
        "enabled": {
          "10": {
            "value": "{color_legacy.blue.60}",
            "type": "color"
          }
        },
        "hover": {
          "10": {
            "value": "{color_legacy.blue.80}",
            "type": "color"
          },
          "20": {
            "value": "{color_legacy.blue.40}",
            "type": "color"
          }
        },
        "active": {
          "10": {
            "value": "{color_legacy.blue.60}",
            "type": "color"
          }
        },
        "emphasis": {
          "default": {
            "value": "{color.haze.700}",
            "type": "color"
          },
          "mid": {
            "value": "{color.azure_blue.300}",
            "type": "color"
          }
        },
        "global_nav": {
          "10": {
            "value": "{color.genesys_navy.600}",
            "type": "color"
          },
          "20": {
            "value": "{color.haze.200}",
            "type": "color"
          },
          "30": {
            "value": "{color.transparent}",
            "type": "color"
          }
        }
      },
      "custom_accents": {
        "ai": {
          "10": {
            "value": "{color.island.500}",
            "type": "color"
          },
          "20": {
            "value": "{color.violet.400}",
            "type": "color"
          },
          "10d": {
            "value": "{color.island.700}",
            "type": "color"
          },
          "20d": {
            "value": "{color.violet.500}",
            "type": "color"
          }
        }
      }
    },
    "border_radius": {
      "interactive": {
        "xlarge": {
          "value": "{border_radius.full}",
          "type": "borderRadius"
        },
        "large": {
          "value": "{border_radius.sm}",
          "type": "borderRadius"
        },
        "small": {
          "value": "{border_radius.sm}",
          "type": "borderRadius"
        },
        "2xl": {
          "value": "{border_radius.lg}",
          "type": "borderRadius",
          "description": "Used only for the toggle, since it needs to have the same value for legacy and flare."
        }
      },
      "container": {
        "large": {
          "value": "{border_radius.sm}",
          "type": "borderRadius"
        },
        "medium": {
          "value": "{border_radius.sm}",
          "type": "borderRadius"
        },
        "small": {
          "value": "{border_radius.sm}",
          "type": "borderRadius"
        }
      },
      "form_control": {
        "input": {
          "large": {
            "value": "{border_radius.sm}",
            "type": "borderRadius"
          },
          "medium": {
            "value": "{border_radius.sm}",
            "type": "borderRadius"
          },
          "small": {
            "value": "{border_radius.sm}",
            "type": "borderRadius"
          }
        }
      },
      "focus": {
        "full": {
          "value": "{border_radius.full}",
          "type": "borderRadius"
        },
        "xlarge": {
          "value": "{border_radius.lg}",
          "type": "borderRadius"
        },
        "large": {
          "value": "{border_radius.md}",
          "type": "borderRadius"
        },
        "medium": {
          "value": "{border_radius.md}",
          "type": "borderRadius"
        },
        "small": {
          "value": "{border_radius.sm}",
          "type": "borderRadius"
        },
        "xsmall": {
          "value": "{border_radius.sm}",
          "type": "borderRadius"
        },
        "2xl": {
          "value": "{border_radius.lg}",
          "type": "borderRadius",
          "description": "Used only for the toggle, since it needs to have the same value for legacy and flare."
        }
      }
    },
    "charts": {
      "categorical_data": {
        "category1": {
          "value": "{color.island.700}",
          "type": "color"
        },
        "category2": {
          "value": "{color.mineral.600}",
          "type": "color"
        },
        "category3": {
          "value": "{color.plum.600}",
          "type": "color"
        },
        "category4": {
          "value": "{color.raspberry.800}",
          "type": "color"
        },
        "category5": {
          "value": "{color.coral.600}",
          "type": "color"
        },
        "category6": {
          "value": "{color.genesys_orange.200}",
          "type": "color"
        },
        "category7": {
          "value": "{color.mango.600}",
          "type": "color"
        },
        "category8": {
          "value": "{color.pear.400}",
          "type": "color"
        },
        "category9": {
          "value": "{color.jade.600}",
          "type": "color"
        },
        "category10": {
          "value": "{color.genesys_navy.700}",
          "type": "color"
        },
        "subtle": {
          "value": "{color.haze.200}",
          "type": "color"
        }
      },
      "numerical_data": {
        "single_color": {
          "level1": {
            "value": "{color.island.100}",
            "type": "color"
          },
          "level2": {
            "value": "{color.island.200}",
            "type": "color"
          },
          "level3": {
            "value": "{color.island.300}",
            "type": "color"
          },
          "level4": {
            "value": "{color.island.400}",
            "type": "color"
          },
          "level5": {
            "value": "{color.island.500}",
            "type": "color"
          },
          "level6": {
            "value": "{color.island.600}",
            "type": "color"
          },
          "level7": {
            "value": "{color.island.700}",
            "type": "color"
          },
          "level8": {
            "value": "{color.island.800}",
            "type": "color"
          },
          "level9": {
            "value": "{color.island.950}",
            "type": "color"
          },
          "level10": {
            "value": "{color.island.1000}",
            "type": "color"
          }
        },
        "multi_color": {
          "green": {
            "value": "{color.island.300}",
            "type": "color"
          },
          "red": {
            "value": "{color.coral.400}",
            "type": "color"
          },
          "yellow": {
            "value": "{color.mango.400}",
            "type": "color"
          }
        }
      },
      "foreground": {
        "10": {
          "value": "{color.white}",
          "type": "color"
        },
        "20": {
          "value": "{color.haze.700}",
          "type": "color"
        },
        "30": {
          "value": "{color.haze.800}",
          "type": "color"
        },
        "40": {
          "value": "{color.haze.900}",
          "type": "color"
        }
      },
      "border": {
        "10": {
          "value": "{color.haze.100}",
          "type": "color"
        },
        "20": {
          "value": "{color.haze.300}",
          "type": "color"
        },
        "30": {
          "value": "{color.haze.400}",
          "type": "color"
        }
      },
      "target_line": {
        "10": {
          "value": "{color.genesys_orange.300}",
          "type": "color"
        }
      },
      "fill": {
        "10": {
          "value": "{color.white}",
          "type": "color"
        }
      },
      "background": {
        "10": {
          "value": "{color.haze.100}",
          "type": "color"
        }
      },
      "sparkline": {
        "mono": {
          "value": "{theme.background.system.primary.40}",
          "type": "color"
        },
        "negative": {
          "value": "{theme.background.system.error.30}",
          "type": "color"
        },
        "positive": {
          "value": "{theme.background.system.success.30}",
          "type": "color"
        },
        "neutral": {
          "value": "{theme.background.system.info.20}",
          "type": "color"
        },
        "trendline": {
          "value": "{theme.background.system.info.10}",
          "type": "color"
        }
      }
    }
  }
}